{
  "weather": [
    {
      "timestamp": "2024-10-09T00:00:00+00:00",
      "source_id": 312070,
      "precipitation": 1.8,
      "pressure_msl": 999.5,
      "sunshine": 0,
      "temperature": 15.1,
      "wind_direction": 290,
      "wind_speed": 12.2,
      "cloud_cover": 100,
      "dew_point": 14.4,
      "relative_humidity": 96,
      "visibility": 20950,
      "wind_gust_direction": 300,
      "wind_gust_speed": 22,
      "condition": "rain",
      "precipitation_probability": 0,
      "precipitation_probability_6h": 0,
      "solar": 0,
      "icon": "rain",
      "City": "berlin"
    },
    {
      "timestamp": "2024-10-09T01:00:00+00:00",
      "source_id": 312070,
      "precipitation": 0.1,
      "pressure_msl": 999.8,
      "sunshine": 0,
      "temperature": 14.8,
      "wind_direction": 280,
      "wind_speed": 10.8,
      "cloud_cover": 100,
      "dew_point": 14.2,
      "relative_humidity": 96,
      "visibility": 45530,
      "wind_gust_direction": 290,
      "wind_gust_speed": 18.7,
      "condition": "rain",
      "precipitation_probability": 0,
      "precipitation_probability_6h": 0,
      "solar": 0,
      "icon": "cloudy",
      "City": "berlin"
    },
    {
      "timestamp": "2024-10-09T02:00:00+00:00",
      "source_id": 312070,
      "precipitation": 0.6,
      "pressure_msl": 1000.1,
      "sunshine": 0,
      "temperature": 14.5,
      "wind_direction": 270,
      "wind_speed": 9,
      "cloud_cover": 100,
      "dew_point": 13.7,
      "relative_humidity": 95,
      "visibility": 36340,
      "wind_gust_direction": 280,
      "wind_gust_speed": 19.8,
      "condition": "rain",
      "precipitation_probability": 0,
      "precipitation_probability_6h": 0,
      "solar": 0,
      "icon": "rain",
      "City": "berlin"
    },
    {
      "timestamp": "2024-10-09T03:00:00+00:00",
      "source_id": 312070,
      "precipitation": 0.1,
      "pressure_msl": 999.6,
      "sunshine": 0,
      "temperature": 14.2,
      "wind_direction": 240,
      "wind_speed": 8.3,
      "cloud_cover": 87,
      "dew_point": 13.4,
      "relative_humidity": 95,
      "visibility": 63180,
      "wind_gust_direction": 240,
      "wind_gust_speed": 14.4,
      "condition": "rain",
      "precipitation_probability": 0,
      "precipitation_probability_6h": 0,
      "solar": 0,
      "icon": "cloudy",
      "City": "berlin"
    },
    {
      "timestamp": "2024-10-09T04:00:00+00:00",
      "source_id": 312070,
      "precipitation": 0.1,
      "pressure_msl": 999.5,
      "sunshine": 0,
      "temperature": 13.3,
      "wind_direction": 200,
      "wind_speed": 13.7,
      "cloud_cover": 100,
      "dew_point": 12.8,
      "relative_humidity": 97,
      "visibility": 17290,
      "wind_gust_direction": 210,
      "wind_gust_speed": 23,
      "condition": "dry",
      "precipitation_probability": 0,
      "precipitation_probability_6h": 0,
      "solar": 0,
      "icon": "cloudy",
      "City": "berlin"
    },
    {
      "timestamp": "2024-10-09T05:00:00+00:00",
      "source_id": 312070,
      "precipitation": 0,
      "pressure_msl": 999.3,
      "sunshine": 0,
      "temperature": 13.5,
      "wind_direction": 200,
      "wind_speed": 14,
      "cloud_cover": 100,
      "dew_point": 13,
      "relative_humidity": 97,
      "visibility": 6230,
      "wind_gust_direction": 200,
      "wind_gust_speed": 22.7,
      "condition": "dry",
      "precipitation_probability": 0,
      "precipitation_probability_6h": 0,
      "solar": 0,
      "icon": "cloudy",
      "City": "berlin"
    },
    {
      "timestamp": "2024-10-09T06:00:00+00:00",
      "source_id": 312070,
      "precipitation": 0,
      "pressure_msl": 999,
      "sunshine": 0,
      "temperature": 13.1,
      "wind_direction": 210,
      "wind_speed": 13,
      "cloud_cover": 100,
      "dew_point": 12.6,
      "relative_humidity": 97,
      "visibility": 6170,
      "wind_gust_direction": 210,
      "wind_gust_speed": 24.8,
      "condition": "dry",
      "precipitation_probability": 0,
      "precipitation_probability_6h": 0,
      "solar": 0.002,
      "icon": "cloudy",
      "City": "berlin"
    },
    {
      "timestamp": "2024-10-09T07:00:00+00:00",
      "source_id": 312070,
      "precipitation": 0,
      "pressure_msl": 999.2,
      "sunshine": 0,
      "temperature": 12.7,
      "wind_direction": 210,
      "wind_speed": 15.5,
      "cloud_cover": 37,
      "dew_point": 12.2,
      "relative_humidity": 97,
      "visibility": 910,
      "wind_gust_direction": 200,
      "wind_gust_speed": 24.5,
      "condition": "dry",
      "precipitation_probability": 0,
      "precipitation_probability_6h": 0,
      "solar": 0.019,
      "icon": "partly-cloudy-day",
      "City": "berlin"
    },
    {
      "timestamp": "2024-10-09T08:00:00+00:00",
      "source_id": 312070,
      "precipitation": 0,
      "pressure_msl": 999.1,
      "sunshine": 57,
      "temperature": 13.7,
      "wind_direction": 190,
      "wind_speed": 16.6,
      "cloud_cover": 12,
      "dew_point": 12.6,
      "relative_humidity": 93,
      "visibility": 25800,
      "wind_gust_direction": 190,
      "wind_gust_speed": 32.8,
      "condition": "dry",
      "precipitation_probability": 0,
      "precipitation_probability_6h": 0,
      "solar": 0.231,
      "icon": "clear-day",
      "City": "berlin"
    },
    {
      "timestamp": "2024-10-09T09:00:00+00:00",
      "source_id": 312070,
      "precipitation": 0,
      "pressure_msl": 998.4,
      "sunshine": 59,
      "temperature": 15.5,
      "wind_direction": 200,
      "wind_speed": 14.8,
      "cloud_cover": 0,
      "dew_point": 13,
      "relative_humidity": 85,
      "visibility": 29120,
      "wind_gust_direction": 190,
      "wind_gust_speed": 32.8,
      "condition": "dry",
      "precipitation_probability": 0,
      "precipitation_probability_6h": 0,
      "solar": 0.351,
      "icon": "clear-day",
      "City": "berlin"
    },
    {
      "timestamp": "2024-10-09T10:00:00+00:00",
      "source_id": 312070,
      "precipitation": 0,
      "pressure_msl": 997.7,
      "sunshine": 60,
      "temperature": 16.9,
      "wind_direction": 200,
      "wind_speed": 14.4,
      "cloud_cover": 25,
      "dew_point": 12.7,
      "relative_humidity": 76,
      "visibility": 75000,
      "wind_gust_direction": 180,
      "wind_gust_speed": 31,
      "condition": "dry",
      "precipitation_probability": 0,
      "precipitation_probability_6h": 0,
      "solar": 0.444,
      "icon": "partly-cloudy-day",
      "City": "berlin"
    },
    {
      "timestamp": "2024-10-09T11:00:00+00:00",
      "source_id": 312070,
      "precipitation": 0,
      "pressure_msl": 997.1,
      "sunshine": 53,
      "temperature": 17.5,
      "wind_direction": 190,
      "wind_speed": 16.6,
      "cloud_cover": 100,
      "dew_point": 12.7,
      "relative_humidity": 73,
      "visibility": 54660,
      "wind_gust_direction": 160,
      "wind_gust_speed": 34.6,
      "condition": "dry",
      "precipitation_probability": 0,
      "precipitation_probability_6h": 0,
      "solar": 0.428,
      "icon": "cloudy",
      "City": "berlin"
    },
    {
      "timestamp": "2024-10-09T12:00:00+00:00",
      "source_id": 312070,
      "precipitation": 0,
      "pressure_msl": 996.4,
      "sunshine": 59,
      "temperature": 18.7,
      "wind_direction": 190,
      "wind_speed": 18,
      "cloud_cover": 100,
      "dew_point": 13,
      "relative_humidity": 69,
      "visibility": 75000,
      "wind_gust_direction": 160,
      "wind_gust_speed": 35.6,
      "condition": "dry",
      "precipitation_probability": 0,
      "precipitation_probability_6h": 0,
      "solar": 0.435,
      "icon": "cloudy",
      "City": "berlin"
    },
    {
      "timestamp": "2024-10-09T13:00:00+00:00",
      "source_id": 312070,
      "precipitation": 0,
      "pressure_msl": 995.6,
      "sunshine": 52,
      "temperature": 19.2,
      "wind_direction": 190,
      "wind_speed": 17.6,
      "cloud_cover": 100,
      "dew_point": 13.1,
      "relative_humidity": 68,
      "visibility": 68460,
      "wind_gust_direction": 190,
      "wind_gust_speed": 37.4,
      "condition": "dry",
      "precipitation_probability": 0,
      "precipitation_probability_6h": 0,
      "solar": 0.373,
      "icon": "cloudy",
      "City": "berlin"
    },
    {
      "timestamp": "2024-10-09T14:00:00+00:00",
      "source_id": 312070,
      "precipitation": 0,
      "pressure_msl": 995.1,
      "sunshine": 15,
      "temperature": 18.3,
      "wind_direction": 180,
      "wind_speed": 18.4,
      "cloud_cover": 100,
      "dew_point": 13,
      "relative_humidity": 71,
      "visibility": 74850,
      "wind_gust_direction": 190,
      "wind_gust_speed": 39.2,
      "condition": "dry",
      "precipitation_probability": 0,
      "precipitation_probability_6h": 0,
      "solar": 0.205,
      "icon": "cloudy",
      "City": "berlin"
    },
    {
      "timestamp": "2024-10-09T15:00:00+00:00",
      "source_id": 312070,
      "precipitation": 0,
      "pressure_msl": 994.6,
      "sunshine": 0,
      "temperature": 17.5,
      "wind_direction": 160,
      "wind_speed": 14,
      "cloud_cover": 87,
      "dew_point": 13.1,
      "relative_humidity": 75,
      "visibility": 58270,
      "wind_gust_direction": 170,
      "wind_gust_speed": 25.2,
      "condition": "dry",
      "precipitation_probability": 0,
      "precipitation_probability_6h": 0,
      "solar": 0.079,
      "icon": "cloudy",
      "City": "berlin"
    },
    {
      "timestamp": "2024-10-09T16:00:00+00:00",
      "source_id": 312070,
      "precipitation": 0,
      "pressure_msl": 994,
      "sunshine": 0,
      "temperature": 15.8,
      "wind_direction": 160,
      "wind_speed": 14.8,
      "cloud_cover": 100,
      "dew_point": 14.1,
      "relative_humidity": 90,
      "visibility": 33530,
      "wind_gust_direction": 160,
      "wind_gust_speed": 23,
      "condition": "dry",
      "precipitation_probability": 0,
      "precipitation_probability_6h": 0,
      "solar": 0.02,
      "icon": "cloudy",
      "City": "berlin"
    },
    {
      "timestamp": "2024-10-09T17:00:00+00:00",
      "source_id": 312070,
      "precipitation": 0,
      "pressure_msl": 993.4,
      "sunshine": 0,
      "temperature": 14.9,
      "wind_direction": 160,
      "wind_speed": 15.1,
      "cloud_cover": 87,
      "dew_point": 13.9,
      "relative_humidity": 94,
      "visibility": 38400,
      "wind_gust_direction": 160,
      "wind_gust_speed": 24.8,
      "condition": "dry",
      "precipitation_probability": 0,
      "precipitation_probability_6h": 0,
      "solar": 0.002,
      "icon": "cloudy",
      "City": "berlin"
    },
    {
      "timestamp": "2024-10-09T18:00:00+00:00",
      "source_id": 312070,
      "precipitation": 0,
      "pressure_msl": 992.3,
      "sunshine": 0,
      "temperature": 14.7,
      "wind_direction": 140,
      "wind_speed": 15.8,
      "cloud_cover": 100,
      "dew_point": 13.9,
      "relative_humidity": 95,
      "visibility": 43000,
      "wind_gust_direction": 130,
      "wind_gust_speed": 25.6,
      "condition": "dry",
      "precipitation_probability": 0,
      "precipitation_probability_6h": 0,
      "solar": 0,
      "icon": "cloudy",
      "City": "berlin"
    },
    {
      "timestamp": "2024-10-09T19:00:00+00:00",
      "source_id": 312070,
      "precipitation": 0,
      "pressure_msl": 991.1,
      "sunshine": 0,
      "temperature": 14.4,
      "wind_direction": 130,
      "wind_speed": 16.6,
      "cloud_cover": 87,
      "dew_point": 13.4,
      "relative_humidity": 94,
      "visibility": 38830,
      "wind_gust_direction": 120,
      "wind_gust_speed": 28.1,
      "condition": "dry",
      "precipitation_probability": 0,
      "precipitation_probability_6h": 0,
      "solar": 0,
      "icon": "cloudy",
      "City": "berlin"
    },
    {
      "timestamp": "2024-10-09T20:00:00+00:00",
      "source_id": 312070,
      "precipitation": 0,
      "pressure_msl": 991,
      "sunshine": 0,
      "temperature": 14.9,
      "wind_direction": 140,
      "wind_speed": 16.6,
      "cloud_cover": 100,
      "dew_point": 13.1,
      "relative_humidity": 89,
      "visibility": 41780,
      "wind_gust_direction": 160,
      "wind_gust_speed": 31.7,
      "condition": "dry",
      "precipitation_probability": 0,
      "precipitation_probability_6h": 0,
      "solar": 0,
      "icon": "cloudy",
      "City": "berlin"
    },
    {
      "timestamp": "2024-10-09T21:00:00+00:00",
      "source_id": 312070,
      "precipitation": 0,
      "pressure_msl": 989.9,
      "sunshine": 0,
      "temperature": 14.4,
      "wind_direction": 140,
      "wind_speed": 15.5,
      "cloud_cover": 100,
      "dew_point": 13.3,
      "relative_humidity": 93,
      "visibility": 56270,
      "wind_gust_direction": 120,
      "wind_gust_speed": 27,
      "condition": "dry",
      "precipitation_probability": 0,
      "precipitation_probability_6h": 0,
      "solar": 0,
      "icon": "cloudy",
      "City": "berlin"
    },
    {
      "timestamp": "2024-10-09T22:00:00+00:00",
      "source_id": 312070,
      "precipitation": 0,
      "pressure_msl": 989,
      "sunshine": 0,
      "temperature": 14.9,
      "wind_direction": 130,
      "wind_speed": 15.8,
      "cloud_cover": 100,
      "dew_point": 12.6,
      "relative_humidity": 86,
      "visibility": 58870,
      "wind_gust_direction": 120,
      "wind_gust_speed": 24.5,
      "condition": "dry",
      "precipitation_probability": 0,
      "precipitation_probability_6h": 0,
      "solar": 0,
      "icon": "cloudy",
      "City": "berlin"
    },
    {
      "timestamp": "2024-10-09T23:00:00+00:00",
      "source_id": 312070,
      "precipitation": 0,
      "pressure_msl": 988.8,
      "sunshine": 0,
      "temperature": 14.5,
      "wind_direction": 140,
      "wind_speed": 15.1,
      "cloud_cover": 100,
      "dew_point": 12.9,
      "relative_humidity": 90,
      "visibility": 26260,
      "wind_gust_direction": 150,
      "wind_gust_speed": 25.2,
      "condition": "dry",
      "precipitation_probability": 0,
      "precipitation_probability_6h": 0,
      "solar": 0,
      "icon": "cloudy",
      "City": "berlin"
    }
  ]
}